LICENSE
MANIFEST.in
README.rst
setup.py
converge/__init__.py
converge/settings.py
converge.egg-info/PKG-INFO
converge.egg-info/SOURCES.txt
converge.egg-info/dependency_links.txt
converge.egg-info/top_level.txt
fortest/__init__.py
settings/__init__.py