Metadata-Version: 2.1
Name: converge
Version: 1.1.1
Summary: Ultra simple settings management for (only) Python apps
Home-page: http://pypi.python.org/pypi/converge/
Author: Shekhar Tiwatne
Author-email: pythonic@gmail.com
License: http://www.opensource.org/licenses/mit-license.php
Platform: UNKNOWN
Classifier: Programming Language :: Python :: 3
Requires-Python: >=3.5
License-File: LICENSE
